LICENSE
MANIFEST.in
README.md
setup.cfg
setup.py
code_attention_visualizer.egg-info/PKG-INFO
code_attention_visualizer.egg-info/SOURCES.txt
code_attention_visualizer.egg-info/dependency_links.txt
code_attention_visualizer.egg-info/requires.txt
code_attention_visualizer.egg-info/top_level.txt
codeattention/__init__.py
codeattention/source_code.py
codeattention/tokenizer.py
codeattention/viz_patch.py
codeattention/assets/FreeMono.ttf