Metadata-Version: 2.1
Name: code-attention-visualizer
Version: 0.0.4
Summary: Visualizer for human attention over source code tokens.
Home-page: https://github.com/MattePalte/codeattention
Author: Matteo Paltenghi
Author-email: mattepalte@live.it
License: UNKNOWN
Platform: UNKNOWN
Classifier: Programming Language :: Python :: 3
Classifier: License :: OSI Approved :: MIT License
Classifier: Operating System :: OS Independent
Requires-Python: >=3.6
